LICENSE
MANIFEST.in
README.md
pyproject.toml
setup.py
docs/amazon.rst
docs/conf.py
docs/imdb.rst
docs/index.rst
docs/inference.rst
docs/iris.rst
docs/make.bat
docs/mnist.rst
docs/requirements.txt
docs/userguide.rst
docs/image/GT_FRONTPAGE_RTD.png
docs/image/Green Tsetlin transparent brown.png
docs/image/Green Tsetlin transparent.png
docs/image/Green Tsetlin transparent.svg
docs/image/Green Tsetlin.png
docs/image/Green Tsetlin.psd
docs/image/Green Tsetlin.svg
docs/image/RTD_LOGO_SMALL.png
docs/notebooks/california_housing_example.ipynb
docs/notebooks/imdb_example.ipynb
green_tsetlin/__init__.py
green_tsetlin/backend.py
green_tsetlin/dataset_generator.py
green_tsetlin/hpsearch.py
green_tsetlin/predictor.py
green_tsetlin/ruleset.py
green_tsetlin/sparse_tsetlin_machine.py
green_tsetlin/trainer.py
green_tsetlin/tsetlin_machine.py
green_tsetlin.egg-info/PKG-INFO
green_tsetlin.egg-info/SOURCES.txt
green_tsetlin.egg-info/dependency_links.txt
green_tsetlin.egg-info/not-zip-safe
green_tsetlin.egg-info/requires.txt
green_tsetlin.egg-info/top_level.txt
green_tsetlin/py_gtc/__init__.py
green_tsetlin/py_gtc/clause_block.py
green_tsetlin/py_gtc/dense_input_block.py
green_tsetlin/py_gtc/executors.py
green_tsetlin/py_gtc/feedback_block.py
green_tsetlin/py_gtc/tsetlin_state.py
green_tsetlin/writers/__init__.py
green_tsetlin/writers/simple_c.py
green_tsetlin/writers/topographical_c.py
src/BS_thread_pool.hpp
src/aligned_tsetlin_state.hpp
src/clause_block.hpp
src/executor.hpp
src/feedback_block.hpp
src/func_avx2.hpp
src/func_conv_avx2.hpp
src/func_conv_tm.hpp
src/func_neon.hpp
src/func_sparse.hpp
src/func_tm.hpp
src/gt_common.hpp
src/inference.hpp
src/input_block.hpp
src/main.cpp
src/random_generator.hpp
src/sparse_tsetlin_state.hpp
tests/test_gtc_avx2_clause_block.py
tests/test_gtc_avx2_conv_clause_block.py
tests/test_gtc_clause_block_base.py
tests/test_gtc_executors.py
tests/test_gtc_feedback_block.py
tests/test_gtc_inference.py
tests/test_gtc_input_block.py
tests/test_gtc_sparse_clause_block.py
tests/test_gtc_tm_clause_block.py
tests/test_gtc_tm_conv_clause_block.py
tests/test_hpsearch.py
tests/test_predictor.py
tests/test_ruleset.py
tests/test_sparse_tsetlin_machine.py
tests/test_trainer.py
