Metadata-Version: 2.4
Name: green_tsetlin
Version: 1.1.0
Summary: A fast Tsetlin Machine impl, based on c++
Home-page: https://github.com/ooki/green_tsetlin
Author: Sondre 'Ooki' Glimsdal
Author-email: sondre.glimsdal@gmail.com
License: MIT
Project-URL: Bug Tracker, https://github.com/ooki/green_tsetlin/issues
Project-URL: Documentation, https://github.com/ooki/green_tsetlin
Project-URL: Source Code, https://github.com/ooki/green_tsetlin
Classifier: Development Status :: 4 - Beta
Classifier: Intended Audience :: Science/Research
Classifier: Intended Audience :: Developers
Classifier: License :: OSI Approved :: MIT License
Classifier: Programming Language :: C++
Classifier: Programming Language :: Python
Classifier: Topic :: Software Development
Classifier: Topic :: Scientific/Engineering
Classifier: Operating System :: Microsoft :: Windows
Classifier: Operating System :: POSIX
Classifier: Operating System :: Unix
Classifier: Operating System :: MacOS
Classifier: Programming Language :: Python :: 3 :: Only
Classifier: Programming Language :: Python :: 3
Classifier: Programming Language :: Python :: 3.8
Classifier: Programming Language :: Python :: 3.9
Classifier: Programming Language :: Python :: 3.10
Classifier: Programming Language :: Python :: 3.11
Classifier: Programming Language :: Python :: 3.12
Requires-Python: >=3.8
License-File: LICENSE
Requires-Dist: numpy>=1.24
Requires-Dist: scipy>=1.10.1
Requires-Dist: scikit-learn>=1.2
Requires-Dist: tqdm>=4.65
Requires-Dist: optuna
Provides-Extra: test
Requires-Dist: pytest; extra == "test"
Dynamic: author
Dynamic: author-email
Dynamic: classifier
Dynamic: description
Dynamic: description-content-type
Dynamic: home-page
Dynamic: license
Dynamic: license-file
Dynamic: project-url
Dynamic: provides-extra
Dynamic: requires-dist
Dynamic: requires-python
Dynamic: summary
